bstblue/__init__.py
bstblue/install.py
bstblue/wbdev.py
bstblue/wbdevtz.py
bstblue/wbyt.py
bstblue-0.1.1.dist-info/LICENSE
bstblue-0.1.1.dist-info/METADATA
bstblue-0.1.1.dist-info/WHEEL
bstblue-0.1.1.dist-info/top_level.txt
bstblue-0.1.1.dist-info/RECORD
