Metadata-Version: 2.1
Name: bstblue
Version: 0.1.1
Summary: bstblue
Home-page: https://github.com/Blueboy0999/bstblue/
Author: Blueboy
Author-email: contact-pypi@blueboy.dev
Project-URL: Bug Tracker, https://github.com/Blueboy0999/bstblue/issues
Classifier: Programming Language :: Python :: 3
Classifier: License :: OSI Approved :: MIT License
Classifier: Operating System :: OS Independent
Requires-Python: >=3.6
License-File: LICENSE
